palet/__init__.py
palet/__main__.py
palet/color.py
palet/model/__init__.py
palet-0.0.0.dist-info/METADATA
palet-0.0.0.dist-info/WHEEL
palet-0.0.0.dist-info/top_level.txt
palet-0.0.0.dist-info/zip-safe
palet-0.0.0.dist-info/RECORD
