Metadata-Version: 2.1
Name: palet
Version: 0.0.0
Summary: Palet is a Python Color Library by Scape Agency.
Home-page: https://www.scape.agency
Download-URL: https://www.scape.agency
Author: Lars van Vianen
Author-email: lars@scape.agency
Maintainer: Scape Agency
Maintainer-email: info@scape.agency
License: MIT
Project-URL: documentation, https://palet.pypa.io/
Project-URL: repository, https://github.com/scape-agency/palet
Keywords: palet,utility,utilities
Classifier: Development Status :: 1 - Planning
Classifier: Intended Audience :: Developers
Classifier: License :: OSI Approved :: MIT License
Classifier: Natural Language :: English
Classifier: Operating System :: OS Independent
Classifier: Programming Language :: Python :: 3 :: Only
Classifier: Topic :: Scientific/Engineering
Classifier: Topic :: Software Development :: Libraries
Requires-Python: >=3.10
